README.rst
setup.py
prett/__init__.py
prett/base.py
prett/multi_types.py
prett/project.py
prett/sender.py
prett/setting.py
prett/widget_interface.py
prett.egg-info/PKG-INFO
prett.egg-info/SOURCES.txt
prett.egg-info/dependency_links.txt
prett.egg-info/requires.txt
prett.egg-info/top_level.txt