Metadata-Version: 1.1
Name: prett
Version: 0.1.0
Summary: A Pretty Project Framework
Home-page: https://github.com/sf-zhou/prett
Author: SF-Zhou
Author-email: sfzhou.scut@gmail.com
License: MIT
Keywords: qt ui
Platform: UNKNOWN
Classifier: Development Status :: 3 - Alpha
Classifier: Intended Audience :: Developers
Classifier: License :: OSI Approved :: MIT License
Classifier: Programming Language :: Python :: 3
Classifier: Programming Language :: Python :: 3.4
